a_pandas_ex_logcat2df/LICENSE
a_pandas_ex_logcat2df/README.MD
a_pandas_ex_logcat2df/__init__.py
a_pandas_ex_logcat2df/requirements.txt
a_pandas_ex_logcat2df/thirdparty.json
a_pandas_ex_logcat2df-0.10.dist-info/LICENSE.rst
a_pandas_ex_logcat2df-0.10.dist-info/METADATA
a_pandas_ex_logcat2df-0.10.dist-info/WHEEL
a_pandas_ex_logcat2df-0.10.dist-info/top_level.txt
a_pandas_ex_logcat2df-0.10.dist-info/RECORD
